{"type":"acfun","update_time":"2026-06-30T01:35:56.190Z","list":[{"index":1,"title":"报告长官！！！★手机竖屏1926★","url":"https://www.acfun.cn/v/ac48649439","hot_value":"6164","extra":{"info":["综合榜Top1","https://www.acfun.cn/rank/list/#cid=-1;range=1;pcid=-3"]}},{"index":2,"title":"来杯好茶摇一摇～爻一爻","url":"https://www.acfun.cn/v/ac48651862","hot_value":"2708","extra":{"info":["综合榜Top2","https://www.acfun.cn/rank/list/#cid=-1;range=1;pcid=-3"]}},{"index":3,"title":"外出酒店不便带灯，只能靠便携灯棒打光","url":"https://www.acfun.cn/v/ac48652240","hot_value":"2189","extra":{"info":["综合榜Top3","https://www.acfun.cn/rank/list/#cid=-1;range=1;pcid=-3"]}},{"index":4,"title":"网络上常见的热门短视频集锦   第三千二百七十四期","url":"https://www.acfun.cn/v/ac48650432","hot_value":"4270","extra":{"info":["综合榜Top4","https://www.acfun.cn/rank/list/#cid=-1;range=1;pcid=-3"]}},{"index":5,"title":"这个理发店在哪里？欢乐八点档-1695","url":"https://www.acfun.cn/v/ac48651427","hot_value":"3962","extra":{"info":["综合榜Top5","https://www.acfun.cn/rank/list/#cid=-1;range=1;pcid=-3"]}},{"index":6,"title":"有点可爱哇","url":"https://www.acfun.cn/v/ac48649511","hot_value":"1757","extra":{"info":["综合榜Top6","https://www.acfun.cn/rank/list/#cid=-1;range=1;pcid=-3"]}},{"index":7,"title":"网络上常见的热门短视频集锦   第三千二百七十三期","url":"https://www.acfun.cn/v/ac48649443","hot_value":"4703","extra":{"info":["综合榜Top7","https://www.acfun.cn/rank/list/#cid=-1;range=1;pcid=-3"]}},{"index":8,"title":"7元一碗，半自助炒饭！搭配十几种酱菜？","url":"https://www.acfun.cn/v/ac48652194","hot_value":"1375","extra":{"info":["综合榜Top8","https://www.acfun.cn/rank/list/#cid=-1;range=1;pcid=-3"]}},{"index":9,"title":"美国印度化，这都能翻车？【岩论606期】","url":"https://www.acfun.cn/v/ac48652599","hot_value":"1477","extra":{"info":["综合榜Top9","https://www.acfun.cn/rank/list/#cid=-1;range=1;pcid=-3"]}},{"index":10,"title":"change","url":"https://www.acfun.cn/v/ac48650709","hot_value":"2409","extra":{"info":["综合榜Top10","https://www.acfun.cn/rank/list/#cid=-1;range=1;pcid=-3"]}},{"index":11,"title":"痒就去洗澡【今天有什么好笑的 #2430】","url":"https://www.acfun.cn/v/ac48651213","hot_value":"2600","extra":{"info":["综合榜Top11","https://www.acfun.cn/rank/list/#cid=-1;range=1;pcid=-3"]}},{"index":12,"title":"Bo Peep Bo Peep","url":"https://www.acfun.cn/v/ac48650708","hot_value":"2742","extra":{"info":["综合榜Top12","https://www.acfun.cn/rank/list/#cid=-1;range=1;pcid=-3"]}},{"index":13,"title":"浙江绍兴美食蒸三臭，咸亨孔乙己套餐，阿星逛鲁迅故里，游兰亭","url":"https://www.acfun.cn/v/ac48650610","hot_value":"1260","extra":{"info":["综合榜Top13","https://www.acfun.cn/rank/list/#cid=-1;range=1;pcid=-3"]}},{"index":14,"title":"赚钱路子，这不就来了","url":"https://www.acfun.cn/v/ac48650745","hot_value":"2507","extra":{"info":["综合榜Top14","https://www.acfun.cn/rank/list/#cid=-1;range=1;pcid=-3"]}},{"index":15,"title":"AEW x NJPW Forbidden Door 2026.06.28","url":"https://www.acfun.cn/v/ac48651655","hot_value":"1978","extra":{"info":["综合榜Top15","https://www.acfun.cn/rank/list/#cid=-1;range=1;pcid=-3"]}},{"index":16,"title":"这个点，邻居们加班都没回家么。。","url":"https://www.acfun.cn/v/ac48652548","hot_value":"1335","extra":{"info":["综合榜Top16","https://www.acfun.cn/rank/list/#cid=-1;range=1;pcid=-3"]}},{"index":17,"title":"重温LiSA初心之作！粤语版《無色透明》，经典永不褪色！","url":"https://www.acfun.cn/v/ac48652241","hot_value":"956","extra":{"info":["综合榜Top17","https://www.acfun.cn/rank/list/#cid=-1;range=1;pcid=-3"]}},{"index":18,"title":"恶魔天胡开局、但却把一手好牌打个稀烂《修女2》招魂宇宙第六篇","url":"https://www.acfun.cn/v/ac48651979","hot_value":"1084","extra":{"info":["综合榜Top18","https://www.acfun.cn/rank/list/#cid=-1;range=1;pcid=-3"]}},{"index":19,"title":"就把我的理想我的人生统统都带走吧( ´▽｀)","url":"https://www.acfun.cn/v/ac48652656","hot_value":"1110","extra":{"info":["综合榜Top19","https://www.acfun.cn/rank/list/#cid=-1;range=1;pcid=-3"]}},{"index":20,"title":"水手妹~So crazy","url":"https://www.acfun.cn/v/ac48650702","hot_value":"2061","extra":{"info":["综合榜Top20","https://www.acfun.cn/rank/list/#cid=-1;range=1;pcid=-3"]}}]}